CHANGES
LICENSE
MANIFEST.in
README.md
setup.py
django_singleton_admin/__init__.py
django_singleton_admin/admin.py
django_singleton_admin/models.py
django_singleton_admin/tests.py
django_singleton_admin/views.py
django_singleton_admin.egg-info/PKG-INFO
django_singleton_admin.egg-info/SOURCES.txt
django_singleton_admin.egg-info/dependency_links.txt
django_singleton_admin.egg-info/not-zip-safe
django_singleton_admin.egg-info/requires.txt
django_singleton_admin.egg-info/top_level.txt
django_singleton_admin/templates/admin/singleton_enabled_base.html