Metadata-Version: 1.0
Name: django-singleton-admin
Version: 0.0.3
Summary: This package provides a way to ensure singleton classes can 
Home-page: https://github.com/RacingTadpole/django-singleton-admin
Author: Arthur Street
Author-email: arthur@racingtadpole.com
License: BSD
Keywords: globals singleton
Platform: UNKNOWN
Classifier: Environment :: Web Environment
Classifier: Framework :: Django
Classifier: Intended Audience :: Developers
Classifier: License :: OSI Approved :: BSD License
Classifier: Operating System :: OS Independent
Classifier: Programming Language :: Python
Classifier: Programming Language :: Python :: 2.7
Classifier: Topic :: Internet :: WWW/HTTP
Classifier: Topic :: Internet :: WWW/HTTP :: Dynamic Content
